VerilogBasics/greater_than.v
module greater_than (A,B,F);
    input [1:0] A,B; // two bit inputs
    output F;
    // assign F = A>B  easier way to do our comparator logic 

    assign F = A[1]&~B[1] | A[1]&A[0]&~B[0] | A[0]&~B[1]&~B[0]; 
    /* 
    
    our greater_than logic design immplementation in a generic way we could have done simply A>B but here we learn a more generic way of doing any logic.

    our optimized greater_than expression, F = A1B1' + A1A0B0' + A0B1'B0'

    */


endmodule

/*
     for a two bit number we use range of indices ex  [1:0] for two bits 
     [3:0] for 4 bits, [7:0] for 8 bit inputs
     
     & for A.B 
     | for A + B

*/

VerilogBasics/greater_than_tb.v
`timescale 1ns/1ns
`include "greater_than.v"

module greater_than_tb;
    reg[1:0] A,B;
    wire F;

    greater_than unit_test(A,B,F);

    initial begin
        $dumpfile("greater_than_tb.vcd");
        $dumpvars(0,greater_than_tb);

        {A,B} = 4'd0; #20; // all cases in truth table
        {A,B} = 4'd1; #20;
        {A,B} = 4'd2; #20;
        {A,B} = 4'd3; #20;
        {A,B} = 4'd4; #20;
        {A,B} = 4'd5; #20;
        {A,B} = 4'd6; #20;
        {A,B} = 4'd7; #20;
        {A,B} = 4'd8; #20;
        {A,B} = 4'd9; #20;
        {A,B} = 4'd10; #20;
        {A,B} = 4'd11; #20;
        {A,B} = 4'd12; #20;
        {A,B} = 4'd13; #20;
        {A,B} = 4'd14; #20;
        {A,B} = 4'd15; #20;
        $display("Test finished...");
    end

endmodule

/*
    {A,B} is a vector notaion it means we treat A (2 bit number) and B(also a 2 bit number) as one sinlge 
    4 bit number 4' means we have a 4 bits as result of vectorizing them d means we specify in deicmal and specify the value 0 in decimal we could do it in binary by using the prefix b followed by 0000 ( since we have 4 bit vector and our value is 0 ) so 4'd0 in decimal, 4'b0000 in binary and #20 is 20 ns delay
*/

VerilogBasics/greater_than_tb.vcd
$date
	Wed Feb 16 10:17:02 2022
$end
$version
	Icarus Verilog
$end
$timescale
	1ns
$end
$scope module greater_than_tb $end
$var wire 1 ! F $end
$var reg 2 " A [1:0] $end
$var reg 2 # B [1:0] $end
$scope module unit_test $end
$var wire 2 $ A [1:0] $end
$var wire 2 % B [1:0] $end
$var wire 1 ! F $end
$upscope $end
$upscope $end
$enddefinitions $end
#0
$dumpvars
b0 %
b0 $
b0 #
b0 "
0!
$end
#20
b1 #
b1 %
#40
b10 #
b10 %
#60
b11 #
b11 %
#80
1!
b1 "
b1 $
b0 #
b0 %
#100
0!
b1 #
b1 %
#120
0!
b10 #
b10 %
#140
b11 #
b11 %
#160
1!
b10 "
b10 $
b0 #
b0 %
#180
b1 #
b1 %
#200
0!
b10 #
b10 %
#220
b11 #
b11 %
#240
1!
b11 "
b11 $
b0 #
b0 %
#260
b1 #
b1 %
#280
b10 #
b10 %
#300
0!
b11 #
b11 %
